{
    "senior": {
        "giocatori": [
            "Dario Amato",
            "Marco Archilli",
            "Paolo Armah",
            "Gianluca Bacchiavini",
            "Mike Billops",
            "Maurizio Bruzzi",
            "Alessandro Bussei",
            "Giovanni Caccialupi",
            "Luca Callegati",
            "Michele Calò",
            "Renato Camposano",
            "Luca Catellani",
            "Marco Innocente Contalbo",
            "Mark Cordes",
            "Riccardo De Leo",
            "Fabio Dibitonto",
            "Manny Diaz",
            "Domenico Errico",
            "Riccardo Fantozzi",
            "Valerio Fantuzzi",
            "Silvio Ferretti",
            "Gianluca Fiorillo",
            "Andrea Fontana",
            "Mattia Fontanesi",
            "Renato Frignani",
            "Mattia Galvano",
            "Pasquale Giacometti",
            "Nicolò Iotti",
            "Gionata Lazzaretti",
            "Leonardo Lazzaretti",
            "Marco Lazzaretti",
            "Damiano Ligabue",
            "Massimiliano Mai",
            "Manuel Mazzani",
            "Niles Reed Mittasch",
            "Davide Mosca",
            "Roberto Musi",
            "Luca Nardini",
            "Riccardo Pallicelli",
            "Marco Prampolini",
            "Davide Ricchetti",
            "Marco Rinaldini",
            "Luca Salvarani",
            "Carlo Silingardi",
            "Alberto Tartaglia",
            "Francesco Tirelli",
            "Massimiliano Trenti",
            "Antwi Osborne Tukpeh",
            "Fabrizio Vaccari",
            "Federico Vigarani",
            "Maurizio Zanni",
            "Roberto Zini"
        ],
        "coach": [
            "Fabio Bartoli",
            "Marco Bonacini",
            "Matteo Bondi",
            "Luca Cattini",
            "Jacopo Cavazzoni",
            "Mauro Giberti",
            "Scott Mackey",
            "Massimiliano Mai",
            "John Mc Keon",
            "Daniele Rossi",
            "Federico Scolari"
        ]
    },
    "scorer": [
        "Cristian Canossini",
        "Barbara Comi",
        "Renata Fontechiari"
    ],
    "medici": [
        "Edoardo Belletti",
        "Fabrizio Bianco",
        "Andrea Cantergiani",
        "Matteo Cipolli"
    ],
    "dirigenti" :[
        "Maurizio Badari",
        "Claudio Bizzarri",
        "Antonio Callegati",
        "Renata Fontechiari",
        "Ettore Maestri",
        "Duilio G. Marco Modica",
        "Manuela Pellegrini",
        "Davide Ruozzi",
        "Federico Scolari",
        "Gianfranco Sessi",
        "Olaf Zanaroli"
    ]
}